soupape/__init__.py
soupape/collection.py
soupape/errors.py
soupape/injector/__init__.py
soupape/injector/async_injector.py
soupape/injector/base.py
soupape/injector/sync_injector.py
soupape/instances.py
soupape/post_init.py
soupape/py.typed
soupape/resolvers/__init__.py
soupape/resolvers/abc.py
soupape/resolvers/collections.py
soupape/resolvers/default.py
soupape/resolvers/funcs.py
soupape/resolvers/instantiated.py
soupape/resolvers/raw.py
soupape/resolvers/utils.py
soupape/types.py
soupape/utils.py
soupape-0.3.0.dist-info/WHEEL
soupape-0.3.0.dist-info/METADATA
soupape-0.3.0.dist-info/RECORD
