Metadata-Version: 2.3
Name: soupape
Version: 0.3.0
Summary: An async dependency injection framework for Python.
Requires-Dist: hafersack>=0.1.0
Requires-Dist: peritype>=0.5.1
Requires-Python: >=3.13
